picoflow/__init__.py
picoflow/core.py
picoflow/adapters/__init__.py
picoflow/adapters/_http.py
picoflow/adapters/ollama.py
picoflow/adapters/openai_compat.py
picoflow/adapters/registry.py
picoflow/adapters/types.py
picoflow/cookbook/minimal-demo/main.py
picoflow/cookbook/multiple-crew/main.py
picoflow/cookbook/simple-chat/main.py
picoflow/cookbook/simple-chat-stream/main.py
picoflow/cookbook/simple-tool/main.py
picoflow/cookbook/trace/main.py
picoflow-0.1.4.dist-info/LICENSE
picoflow-0.1.4.dist-info/METADATA
picoflow-0.1.4.dist-info/WHEEL
picoflow-0.1.4.dist-info/top_level.txt
picoflow-0.1.4.dist-info/RECORD
