Metadata-Version: 2.1
Name: picoflow
Version: 0.1.4
Summary: Simple, flexible AI agent framework with a small DSL and explicit state
Author: PicoFlow Contributors
License: MIT
Project-URL: Homepage, https://github.com/the-picoflow/picoflow
Project-URL: Repository, https://github.com/the-picoflow/picoflow
Project-URL: Issues, https://github.com/the-picoflow/picoflow/issues
Classifier: Development Status :: 3 - Alpha
Classifier: Intended Audience :: Developers
Classifier: License :: OSI Approved :: MIT License
Classifier: Programming Language :: Python :: 3
Classifier: Programming Language :: Python :: 3.8
Classifier: Programming Language :: Python :: 3.9
Classifier: Programming Language :: Python :: 3.10
Classifier: Programming Language :: Python :: 3.11
Classifier: Topic :: Software Development :: Libraries
Classifier: Topic :: Scientific/Engineering :: Artificial Intelligence
Requires-Python: >=3.8
License-File: LICENSE
